opencc_pyo3/__init__.py
opencc_pyo3/__main__.py
opencc_pyo3/office_helper.py
opencc_pyo3/opencc_pyo3.abi3.so
opencc_pyo3/opencc_pyo3.pyi
opencc_pyo3/pdfium/macos-x64/libpdfium.dylib
opencc_pyo3/pdfium_helper.py
opencc_pyo3/pdfium_loader.py
opencc_pyo3-0.8.7.dist-info/METADATA
opencc_pyo3-0.8.7.dist-info/WHEEL
opencc_pyo3-0.8.7.dist-info/entry_points.txt
opencc_pyo3-0.8.7.dist-info/licenses/LICENSE
opencc_pyo3-0.8.7.dist-info/RECORD
