Metadata-Version: 2.4
Name: opencc_pyo3
Version: 0.8.7
Classifier: Programming Language :: Rust
Classifier: Programming Language :: Python :: 3
Classifier: Programming Language :: Python :: 3.8
Classifier: Programming Language :: Python :: 3.9
Classifier: Programming Language :: Python :: 3.10
Classifier: Programming Language :: Python :: 3.11
Classifier: Programming Language :: Python :: 3.12
Classifier: Programming Language :: Python :: 3.13
Classifier: Programming Language :: Python :: 3.14
Classifier: Programming Language :: Python :: Implementation :: CPython
Classifier: Programming Language :: Python :: Implementation :: PyPy
Classifier: License :: OSI Approved :: MIT License
Classifier: Operating System :: OS Independent
License-File: LICENSE
Summary: A Python extension module powered by Rust and PyO3, providing fast and accurate Chinese text conversion.
Author-email: laisuk <laisuk@yahoo.com>
License: MIT
Requires-Python: >=3.8
Project-URL: ChangeLog, https://github.com/laisuk/opencc_pyo3/blob/master/CHANGELOG.md
Project-URL: Homepage, https://github.com/laisuk/opencc_pyo3
Project-URL: Issues, https://github.com/laisuk/opencc_pyo3/issues
